shaoxia2000_mcp_demo/__init__.py
shaoxia2000_mcp_demo-0.1.0.dist-info/WHEEL
shaoxia2000_mcp_demo-0.1.0.dist-info/entry_points.txt
shaoxia2000_mcp_demo-0.1.0.dist-info/METADATA
shaoxia2000_mcp_demo-0.1.0.dist-info/RECORD
