Metadata-Version: 2.3
Name: shaoxia2000-mcp-demo
Version: 0.1.0
Summary: Add your description here
Author: shaoxia2019
Author-email: shaoxia2019 <baobei_cy@163.com>
Requires-Dist: mcp[cli]>=1.13.1
Requires-Python: >=3.13
